check_pa/__init__.py
check_pa/check_paloalto.py
check_pa/utils.py
check_pa/xml_reader.py
check_pa/modules/__init__.py
check_pa/modules/antivirus.py
check_pa/modules/bgp.py
check_pa/modules/certificate.py
check_pa/modules/cluster.py
check_pa/modules/diskspace.py
check_pa/modules/environmental.py
check_pa/modules/interface.py
check_pa/modules/licenses.py
check_pa/modules/load.py
check_pa/modules/powersupply.py
check_pa/modules/pppoe.py
check_pa/modules/qos.py
check_pa/modules/reports.py
check_pa/modules/sessioninfo.py
check_pa/modules/thermal.py
check_pa/modules/threat.py
check_pa/modules/throughput.py
check_pa/modules/useragent.py
check_paloalto_ng-0.8.1.dist-info/licenses/AUTHORS.rst
check_paloalto_ng-0.8.1.dist-info/licenses/LICENSE
check_paloalto_ng-0.8.1.dist-info/METADATA
check_paloalto_ng-0.8.1.dist-info/WHEEL
check_paloalto_ng-0.8.1.dist-info/entry_points.txt
check_paloalto_ng-0.8.1.dist-info/top_level.txt
check_paloalto_ng-0.8.1.dist-info/RECORD
